aquaref/__init__.py
aquaref/basic.py
aquaref/library/__init__.py
aquaref/test.1.py
aquaref/test.realtaiizor.1.py
aquaref/winforms/__init__.py
aquaref/winforms/application.py
aquaref/winforms/button.py
aquaref/winforms/control.py
aquaref/winforms/form.py
aquaref/winforms/label.py
aquaref/winforms/py.ico
aquaref/winforms/realtaiizor/__init__.py
aquaref/winforms/tooltip.py
aquaref/wpf/__init__.py
aquaref/wpf/code.py
aquaref/wpf/gui.xaml
aquaref/wpf/thread.py
aquaref/wpf/window.py
aquaref-0.0.1a1.dist-info/METADATA
aquaref-0.0.1a1.dist-info/WHEEL
aquaref-0.0.1a1.dist-info/RECORD
